{
    "Critter1": {
        "location": "Jungle Perimeter",
        "baseExp": 2,
        "baseShinyRate": 0.05,
        "shiny": "Critter1A",
        "effForBonus": 35
    },
    "Critter2": {
        "location": "Salty Shores",
        "baseExp": 8,
        "baseShinyRate": 0.03,
        "shiny": "Critter2A",
        "effForBonus": 400
    },
    "Critter3": {
        "location": "The Ring",
        "baseExp": 25,
        "baseShinyRate": 0.02,
        "shiny": "Critter3A",
        "effForBonus": 1500
    },
    "Critter4": {
        "location": "Rats Nest",
        "baseExp": 50,
        "baseShinyRate": 0.01,
        "shiny": "Critter4A",
        "effForBonus": 3500
    },
    "Critter5": {
        "location": "Hollowed Trunk",
        "baseExp": 80,
        "baseShinyRate": 0.006,
        "shiny": "Critter5A",
        "effForBonus": 8000
    },
    "Critter6": {
        "location": "The Stache Split",
        "baseExp": 125,
        "baseShinyRate": 0.003,
        "shiny": "Critter6A",
        "effForBonus": 15000
    },
    "Critter7": {
        "location": "Thermonuclear Climb",
        "baseExp": 160,
        "baseShinyRate": 0.0015,
        "shiny": "Critter7A",
        "effForBonus": 45000
    },
    "Critter8": {
        "location": "Efaunt's Tomb",
        "baseExp": 200,
        "baseShinyRate": 0.0006,
        "shiny": "Critter8A",
        "effForBonus": 100000
    },
    "Critter9": {
        "location": "Wam Wonderland",
        "baseExp": 260,
        "baseShinyRate": 0.0002,
        "shiny": "Critter9A",
        "effForBonus": 200000
    },
    "Critter10": {
        "location": "Cocoa Tunnel",
        "baseExp": 350,
        "baseShinyRate": 3e-05,
        "shiny": "Critter10A",
        "effForBonus": 500000
    }
}