{
    "0": {"name": "Power", "effect": "@Base Damage", "dk": 30, "bonus": 3},
    "1": {"name": "Speed", "effect": "%@Move Speed", "dk": 65, "bonus": 0.1},
    "2": {"name": "Mining", "effect": "@Mining Power", "dk": 280, "bonus": 0.3},
    "3": {"name": "Feasty", "effect": "%@Food Effect", "dk": 320, "bonus": 1},
    "4": {"name": "Health", "effect": "@Base Health", "dk": 0, "bonus": 3},
    "5": {"name": "Kachow", "effect": "%@Crit Damage", "dk": -15, "bonus": 0.4},
    "6": {"name": "Lumberbob", "effect": "@Choppin Power", "dk": 90, "bonus": 0.3},
    "7": {"name": "Thicc Skin", "effect": "@Base Defence", "dk": 210, "bonus": 1},
    "8": {"name": "Oceanman", "effect": "@Fishing Power", "dk": 115, "bonus": 0.3},
    "9": {"name": "Ol Reliable", "effect": "@Catchin Power", "dk": 45, "bonus": 0.3},
    "10": {"name": "Exp", "effect": "%@Class Exp", "dk": 0, "bonus": 0.1},
    "11": {"name": "Anvil", "effect": "%@Product Spd", "dk": 165, "bonus": 0.5},
    "12": {"name": "Cauldron", "effect": "%@Alchemy Exp", "dk": 280, "bonus": 0.5},
    "13": {"name": "Beholder", "effect": "%@Crit Chance", "dk": 300, "bonus": 0.2},
    "14": {"name": "Bullseye", "effect": "%@Accuracy", "dk": 110, "bonus": 0.8},
    "15": {"name": "Box", "effect": "@Trappin Power", "dk": 180, "bonus": 0.3},
    "16": {"name": "Twosoul", "effect": "@Worship Power", "dk": 260, "bonus": 0.3},
    "17": {"name": "Ehexpee", "effect": "%@Skill Exp", "dk": 69, "bonus": 0.1},
    "18": {"name": "Seesaw", "effect": "%@Cons Exp", "dk": 13, "bonus": 0.5},
    "19": {"name": "Pecunia", "effect": "%@Coins", "dk": 50, "bonus": 1},
    "20": {"name": "Mutton", "effect": "%@Cooking Exp", "dk": 0, "bonus": 0.3},
    "21": {"name": "Egg", "effect": "%@Breeding Exp", "dk": 25, "bonus": 0.4},
    "22": {"name": "Battleaxe", "effect": "%@Damage", "dk": 300, "bonus": 0.2},
    "23": {"name": "Spiral", "effect": "%@Divinity Exp", "dk": 70, "bonus": 1},
    "24": {"name": "Boat", "effect": "%@Sailing Spd", "dk": 210, "bonus": 0.5},
    "25": {"name": "Compost", "effect": "%@Farming Exp", "dk": 75, "bonus": 0.4},
    "26": {"name": "Stealth", "effect": "%@Stealth", "dk": 185, "bonus": 0.3},
    "27": {"name": "Essence", "effect": "%@White Ess", "dk": 160, "bonus": 0.6},
    "28": {"name": "Dragon", "effect": "%@Statues Bonus", "dk": 270, "bonus": 0.2}
}