{
    "new": {
        "Bonus 10": {
            "effect": "+{% Cash from Mobs",
            "x1": 20,
            "x2": 100,
            "func": "decay",
            "type": "%",
            "lvlUpText": "+{% Cash"
        },
        "Bonus 15": {
            "effect": "+{ Starting TD Pts",
            "x1": 1,
            "x2": 0,
            "func": "add",
            "type": "",
            "lvlUpText": "+{ Worship Pts"
        },
        "Bonus 12": {
            "effect": "+{% Class EXP gain",
            "x1": 20,
            "x2": 100,
            "func": "decay",
            "type": "%",
            "lvlUpText": "+{% EXP"
        },
        "Bonus 16": {
            "effect": "+{ Tab 1 Talent Pt",
            "x1": 1,
            "x2": 10,
            "func": "intervalAdd",
            "type": "",
            "lvlUpText": "+{ Talent Pt"
        },
        "Bonus 9": {
            "effect": "+{% Catching EXP gain",
            "x1": 50,
            "x2": 100,
            "func": "decay",
            "type": "%",
            "lvlUpText": "+{% Catch EXP"
        },
        "Bonus 17": {
            "effect": "+{ Weapon Power",
            "x1": 0.07,
            "x2": 0,
            "func": "add",
            "type": "",
            "lvlUpText": "+{ Wep POW"
        },
        "Bonus 14": {
            "effect": "+{% Trapping EXP",
            "x1": 50,
            "x2": 100,
            "func": "decay",
            "type": "%",
            "lvlUpText": "+{% Trap EXP"
        },
        "Bonus 11": {
            "effect": "+{% Cash from Mobs",
            "x1": 30,
            "x2": 100,
            "func": "decay",
            "type": "%",
            "lvlUpText": "+{% Cash"
        }
    },
    "changes": {}
}